<?xml version="1.0" encoding="UTF-8"?>
<MetaDataObject xmlns="http://v8.1c.ru/8.3/MDClasses" xmlns:app="http://v8.1c.ru/8.2/managed-application/core" xmlns:cfg="http://v8.1c.ru/8.1/data/enterprise/current-config" xmlns:cmi="http://v8.1c.ru/8.2/managed-application/cmi" xmlns:ent="http://v8.1c.ru/8.1/data/enterprise" xmlns:lf="http://v8.1c.ru/8.2/managed-application/logform" xmlns:style="http://v8.1c.ru/8.1/data/ui/style" xmlns:sys="http://v8.1c.ru/8.1/data/ui/fonts/system" xmlns:v8="http://v8.1c.ru/8.1/data/core" xmlns:v8ui="http://v8.1c.ru/8.1/data/ui" xmlns:web="http://v8.1c.ru/8.1/data/ui/colors/web" xmlns:win="http://v8.1c.ru/8.1/data/ui/colors/windows" xmlns:xen="http://v8.1c.ru/8.3/xcf/enums" xmlns:xpr="http://v8.1c.ru/8.3/xcf/predef" xmlns:xr="http://v8.1c.ru/8.3/xcf/readable" xmlns:xs="http://www.w3.org/2001/XMLSchema" xmlns:xsi="http://www.w3.org/2001/XMLSchema-instance" version="2.20">
	<Constant uuid="4fbfd537-0875-4319-96f2-5297935d19db">
		<InternalInfo>
			<xr:GeneratedType name="ConstantManager.РежимВосстановленияСообщениямиКОД" category="Manager">
				<xr:TypeId>5366f2fe-4be6-430f-880c-4b25b9b0e5d2</xr:TypeId>
				<xr:ValueId>7d3cdd23-2775-43af-872c-587cb3fa5aca</xr:ValueId>
			</xr:GeneratedType>
			<xr:GeneratedType name="ConstantValueManager.РежимВосстановленияСообщениямиКОД" category="ValueManager">
				<xr:TypeId>bd7562fe-017c-48d6-912a-0169d795dc39</xr:TypeId>
				<xr:ValueId>655c0f7f-4341-4961-bd48-afc6bdf2ee6a</xr:ValueId>
			</xr:GeneratedType>
			<xr:GeneratedType name="ConstantValueKey.РежимВосстановленияСообщениямиКОД" category="ValueKey">
				<xr:TypeId>93c1e3ca-a058-59b2-a057-74de97fc6333</xr:TypeId>
				<xr:ValueId>8ee5be87-e0e7-5933-9e1f-eb983921799d</xr:ValueId>
			</xr:GeneratedType>
		</InternalInfo>
		<Properties>
			<Name>РежимВосстановленияСообщениямиКОД</Name>
			<Synonym>
				<v8:item>
					<v8:lang>ru</v8:lang>
					<v8:content>Режим восстановления сообщениями КОД</v8:content>
				</v8:item>
			</Synonym>
			<Comment/>
			<Type>
				<v8:Type>cfg:EnumRef.РежимыВосстановленияСообщениямиКОД</v8:Type>
			</Type>
			<UseStandardCommands>false</UseStandardCommands>
			<DefaultForm/>
			<ExtendedPresentation/>
			<Explanation/>
			<PasswordMode>false</PasswordMode>
			<Format/>
			<EditFormat/>
			<ToolTip/>
			<MarkNegatives>false</MarkNegatives>
			<Mask/>
			<MultiLine>false</MultiLine>
			<ExtendedEdit>false</ExtendedEdit>
			<MinValue xsi:nil="true"/>
			<MaxValue xsi:nil="true"/>
			<FillChecking>DontCheck</FillChecking>
			<ChoiceFoldersAndItems>Items</ChoiceFoldersAndItems>
			<ChoiceParameterLinks/>
			<ChoiceParameters/>
			<QuickChoice>Auto</QuickChoice>
			<ChoiceForm/>
			<LinkByType/>
			<ChoiceHistoryOnInput>Auto</ChoiceHistoryOnInput>
			<DataLockControlMode>Managed</DataLockControlMode>
			<DataHistory>DontUse</DataHistory>
			<UpdateDataHistoryImmediatelyAfterWrite>false</UpdateDataHistoryImmediatelyAfterWrite>
			<ExecuteAfterWriteDataHistoryVersionProcessing>false</ExecuteAfterWriteDataHistoryVersionProcessing>
		</Properties>
	</Constant>
</MetaDataObject>